midas_civil/_BoundaryChangeAssignment.py
midas_civil/__init__.py
midas_civil/_analysiscontrol.py
midas_civil/_boundary.py
midas_civil/_construction.py
midas_civil/_element.py
midas_civil/_group.py
midas_civil/_load.py
midas_civil/_loadcomb.py
midas_civil/_mapi.py
midas_civil/_material.py
midas_civil/_model.py
midas_civil/_movingload.py
midas_civil/_node.py
midas_civil/_result_table.py
midas_civil/_result_test.py
midas_civil/_settlement.py
midas_civil/_temperature.py
midas_civil/_tendon.py
midas_civil/_thickness.py
midas_civil/_utils.py
midas_civil/_view.py
midas_civil/_view_trial.py
midas_civil/_visualise.py
midas_civil/_section/_TapdbSecSS.py
midas_civil/_section/__init__.py
midas_civil/_section/_compositeSS.py
midas_civil/_section/_dbSecSS.py
midas_civil/_section/_offsetSS.py
midas_civil/_section/_pscSS copy.py
midas_civil/_section/_pscSS.py
midas_civil/_section/_tapPSC12CellSS.py
midas_civil/_section/_unSupp.py
midas_civil/_utilsFunc/__init__.py
midas_civil/_utilsFunc/_line2plate.py
midas_civil-1.4.2.dist-info/licenses/LICENSE
midas_civil-1.4.2.dist-info/METADATA
midas_civil-1.4.2.dist-info/WHEEL
midas_civil-1.4.2.dist-info/top_level.txt
midas_civil-1.4.2.dist-info/RECORD
