Metadata-Version: 2.4
Name: midas_civil
Version: 1.4.2
Summary: Python library for MIDAS Civil NX
Home-page: https://github.com/MIDASIT-Co-Ltd/midas-civil-python
Author: Sumit Shekhar
Author-email: sumit.midasit@gmail.com
License: MIT
Keywords: midas,civil,civil nx,bridge
License-File: LICENSE
Requires-Dist: numpy
Requires-Dist: polars
Requires-Dist: requests
Requires-Dist: scipy
Requires-Dist: colorama
Requires-Dist: openpyxl
Requires-Dist: tqdm
Requires-Dist: gmsh
Dynamic: author
Dynamic: author-email
Dynamic: description
Dynamic: description-content-type
Dynamic: home-page
Dynamic: keywords
Dynamic: license
Dynamic: license-file
Dynamic: requires-dist
Dynamic: summary
